carbspec/__init__.py
carbspec/helpers.py
carbspec/io.py
carbspec/.vscode/tags
carbspec/alkalinity/TA.py
carbspec/alkalinity/__init__.py
carbspec/alkalinity/acidcal.py
carbspec/alkalinity/species.py
carbspec/alkalinity/uncertainty.py
carbspec/cmd/__init__.py
carbspec/cmd/plot.py
carbspec/cmd/reprocessing.py
carbspec/cmd/session.py
carbspec/cmd/utils.py
carbspec/cmd/resources/TA_weights.ods
carbspec/cmd/resources/carbspec.cfg
carbspec/dye/Ks.py
carbspec/dye/__init__.py
carbspec/dye/peaks.py
carbspec/dye/spline_creation.ipynb
carbspec/dye/splines.py
carbspec/gui/__init__.py
carbspec/gui/app.py
carbspec/gui/graph.py
carbspec/gui/measurePane.py
carbspec/gui/program.py
carbspec/gui/setupPane.py
carbspec/gui/statusLED.py
carbspec/gui/styles.py
carbspec/gui/stylesheet.qss
carbspec/gui/resources/carbspec.cfg
carbspec/instruments/__init__.py
carbspec/instruments/beamswitch_FT232H.py
carbspec/instruments/beamswitch_rpi.py
carbspec/instruments/dummy.py
carbspec/instruments/instrument.py
carbspec/instruments/spectrometer.py
carbspec/instruments/temperature.py
carbspec/resources/splines.json
carbspec/spectro/__init__.py
carbspec/spectro/fitting.py
carbspec/spectro/mixture.py
carbspec/spectro/spectrum.py
carbspec/spectro/two_point.py
carbspec/spectro/uncertainty.py
carbspec-0.0.2.dist-info/METADATA
carbspec-0.0.2.dist-info/WHEEL
carbspec-0.0.2.dist-info/top_level.txt
carbspec-0.0.2.dist-info/zip-safe
carbspec-0.0.2.dist-info/RECORD
