Metadata-Version: 2.1
Name: carbspec
Version: 0.0.2
Summary: Tools for calculating pH and Alkalinity from spectrophotometric data.
Home-page: https://github.com/oscarbranson/carbspec
Author: Oscar Branson
Author-email: ob266@cam.ac.uk
License: 'MIT'
Keywords: science,chemistry,oceanography,carbon
Classifier: Programming Language :: Python :: 3
Classifier: Intended Audience :: Science/Research
